[
  {
    "type": "move",
    "x": 1097.7109375,
    "y": 689.484375,
    "time": 1.4665
  },
  {
    "type": "move",
    "x": 1092.91796875,
    "y": 689.484375,
    "time": 1.4711
  },
  {
    "type": "move",
    "x": 1084.16796875,
    "y": 689.484375,
    "time": 1.4791
  },
  {
    "type": "move",
    "x": 1075.41796875,
    "y": 690.73046875,
    "time": 1.487
  },
  {
    "type": "move",
    "x": 1061.51953125,
    "y": 693.81640625,
    "time": 1.495
  },
  {
    "type": "move",
    "x": 1050.34375,
    "y": 698.00390625,
    "time": 1.5031
  },
  {
    "type": "move",
    "x": 1036.4453125,
    "y": 701.08984375,
    "time": 1.5109
  },
  {
    "type": "move",
    "x": 1022.546875,
    "y": 704.17578125,
    "time": 1.5187
  },
  {
    "type": "move",
    "x": 1008.6484375,
    "y": 707.26171875,
    "time": 1.5269
  },
  {
    "type": "move",
    "x": 994.75,
    "y": 708.8046875,
    "time": 1.5355
  },
  {
    "type": "move",
    "x": 977.82421875,
    "y": 710.49609375,
    "time": 1.5433
  },
  {
    "type": "move",
    "x": 960.8984375,
    "y": 710.49609375,
    "time": 1.5514
  },
  {
    "type": "move",
    "x": 940.64453125,
    "y": 710.49609375,
    "time": 1.5593
  },
  {
    "type": "move",
    "x": 899.140625,
    "y": 710.49609375,
    "time": 1.5675
  },
  {
    "type": "move",
    "x": 871.31640625,
    "y": 706.21484375,
    "time": 1.5759
  },
  {
    "type": "move",
    "x": 843.4921875,
    "y": 697.65234375,
    "time": 1.5838
  },
  {
    "type": "move",
    "x": 829.59375,
    "y": 693.01953125,
    "time": 1.5921
  },
  {
    "type": "move",
    "x": 801.76953125,
    "y": 682.31640625,
    "time": 1.6003
  },
  {
    "type": "move",
    "x": 777.8828125,
    "y": 674.3515625,
    "time": 1.6084
  },
  {
    "type": "move",
    "x": 752.19921875,
    "y": 663.6484375,
    "time": 1.6162
  },
  {
    "type": "move",
    "x": 735.2734375,
    "y": 656.87890625,
    "time": 1.6244
  },
  {
    "type": "move",
    "x": 730.48046875,
    "y": 654.00390625,
    "time": 1.6326
  },
  {
    "type": "move",
    "x": 719.3046875,
    "y": 648.4140625,
    "time": 1.6407
  },
  {
    "type": "move",
    "x": 708.12890625,
    "y": 642.82421875,
    "time": 1.6489
  },
  {
    "type": "move",
    "x": 694.58984375,
    "y": 632.66796875,
    "time": 1.657
  },
  {
    "type": "move",
    "x": 692.1484375,
    "y": 630.2265625,
    "time": 1.665
  },
  {
    "type": "move",
    "x": 681.3359375,
    "y": 620.9609375,
    "time": 1.6732
  },
  {
    "type": "move",
    "x": 679.99609375,
    "y": 618.953125,
    "time": 1.6813
  },
  {
    "type": "move",
    "x": 674.99609375,
    "y": 611.453125,
    "time": 1.6893
  },
  {
    "type": "move",
    "x": 672.12109375,
    "y": 606.66015625,
    "time": 1.6975
  },
  {
    "type": "move",
    "x": 670.203125,
    "y": 601.8671875,
    "time": 1.7055
  },
  {
    "type": "move",
    "x": 667.9921875,
    "y": 595.2421875,
    "time": 1.7138
  },
  {
    "type": "move",
    "x": 667.03125,
    "y": 590.44921875,
    "time": 1.7218
  },
  {
    "type": "move",
    "x": 667.03125,
    "y": 585.65625,
    "time": 1.7299
  },
  {
    "type": "move",
    "x": 667.03125,
    "y": 574.48046875,
    "time": 1.7379
  },
  {
    "type": "move",
    "x": 667.03125,
    "y": 569.6875,
    "time": 1.7461
  },
  {
    "type": "move",
    "x": 667.03125,
    "y": 563.0625,
    "time": 1.7542
  },
  {
    "type": "move",
    "x": 669.52734375,
    "y": 554.3125,
    "time": 1.7623
  },
  {
    "type": "move",
    "x": 674.5234375,
    "y": 546.8125,
    "time": 1.7704
  },
  {
    "type": "move",
    "x": 681.50390625,
    "y": 537.03125,
    "time": 1.7787
  },
  {
    "type": "move",
    "x": 690.765625,
    "y": 526.21875,
    "time": 1.7865
  },
  {
    "type": "move",
    "x": 700.02734375,
    "y": 515.40625,
    "time": 1.7947
  },
  {
    "type": "move",
    "x": 711.87109375,
    "y": 501.8671875,
    "time": 1.8027
  },
  {
    "type": "move",
    "x": 722.6796875,
    "y": 491.0546875,
    "time": 1.8107
  },
  {
    "type": "move",
    "x": 739.24609375,
    "y": 478.16796875,
    "time": 1.819
  },
  {
    "type": "move",
    "x": 754.47265625,
    "y": 468.01171875,
    "time": 1.8271
  },
  {
    "type": "move",
    "x": 769.69921875,
    "y": 457.85546875,
    "time": 1.8352
  },
  {
    "type": "move",
    "x": 791.58984375,
    "y": 445.91015625,
    "time": 1.8435
  },
  {
    "type": "move",
    "x": 809.99609375,
    "y": 436.703125,
    "time": 1.8515
  },
  {
    "type": "move",
    "x": 830.24609375,
    "y": 429.3359375,
    "time": 1.8596
  },
  {
    "type": "move",
    "x": 850.49609375,
    "y": 423.8125,
    "time": 1.8678
  },
  {
    "type": "move",
    "x": 870.74609375,
    "y": 418.2890625,
    "time": 1.8757
  },
  {
    "type": "move",
    "x": 890.99609375,
    "y": 416.4453125,
    "time": 1.8836
  },
  {
    "type": "move",
    "x": 911.24609375,
    "y": 416.4453125,
    "time": 1.8963
  },
  {
    "type": "move",
    "x": 928.16796875,
    "y": 416.4453125,
    "time": 1.8999
  },
  {
    "type": "move",
    "x": 945.08984375,
    "y": 416.4453125,
    "time": 1.9081
  },
  {
    "type": "move",
    "x": 958.984375,
    "y": 416.4453125,
    "time": 1.9163
  },
  {
    "type": "move",
    "x": 970.15625,
    "y": 417.83984375,
    "time": 1.9241
  },
  {
    "type": "move",
    "x": 981.328125,
    "y": 423.42578125,
    "time": 1.9319
  },
  {
    "type": "move",
    "x": 991.10546875,
    "y": 430.40625,
    "time": 1.9399
  },
  {
    "type": "move",
    "x": 1001.9140625,
    "y": 439.66796875,
    "time": 1.9484
  },
  {
    "type": "move",
    "x": 1011.17578125,
    "y": 450.4765625,
    "time": 1.9563
  },
  {
    "type": "move",
    "x": 1021.328125,
    "y": 464.01171875,
    "time": 1.9648
  },
  {
    "type": "move",
    "x": 1029.046875,
    "y": 476.36328125,
    "time": 1.9727
  },
  {
    "type": "move",
    "x": 1038.25,
    "y": 494.76953125,
    "time": 1.981
  },
  {
    "type": "move",
    "x": 1043.32421875,
    "y": 511.69140625,
    "time": 1.9888
  },
  {
    "type": "move",
    "x": 1048.84375,
    "y": 531.94140625,
    "time": 1.9971
  },
  {
    "type": "move",
    "x": 1052.5234375,
    "y": 552.19140625,
    "time": 2.0052
  },
  {
    "type": "move",
    "x": 1056.203125,
    "y": 572.44140625,
    "time": 2.0133
  },
  {
    "type": "move",
    "x": 1058.19140625,
    "y": 596.32421875,
    "time": 2.0214
  },
  {
    "type": "move",
    "x": 1058.19140625,
    "y": 616.57421875,
    "time": 2.0294
  },
  {
    "type": "move",
    "x": 1058.19140625,
    "y": 633.49609375,
    "time": 2.0375
  },
  {
    "type": "move",
    "x": 1058.19140625,
    "y": 650.41796875,
    "time": 2.0455
  },
  {
    "type": "move",
    "x": 1058.19140625,
    "y": 664.3125,
    "time": 2.0536
  },
  {
    "type": "move",
    "x": 1056.64453125,
    "y": 678.20703125,
    "time": 2.0617
  },
  {
    "type": "move",
    "x": 1051.0546875,
    "y": 687.984375,
    "time": 2.0698
  },
  {
    "type": "move",
    "x": 1045.46484375,
    "y": 697.76171875,
    "time": 2.0779
  },
  {
    "type": "move",
    "x": 1039.21484375,
    "y": 705.2578125,
    "time": 2.0859
  },
  {
    "type": "move",
    "x": 1031.71484375,
    "y": 711.50390625,
    "time": 2.0939
  },
  {
    "type": "move",
    "x": 1021.93359375,
    "y": 717.08984375,
    "time": 2.1019
  },
  {
    "type": "move",
    "x": 1010.7578125,
    "y": 722.67578125,
    "time": 2.1101
  },
  {
    "type": "move",
    "x": 996.859375,
    "y": 725.76171875,
    "time": 2.1183
  },
  {
    "type": "move",
    "x": 979.93359375,
    "y": 729.14453125,
    "time": 2.1267
  },
  {
    "type": "move",
    "x": 959.6796875,
    "y": 730.984375,
    "time": 2.1345
  },
  {
    "type": "move",
    "x": 942.75390625,
    "y": 732.67578125,
    "time": 2.1426
  },
  {
    "type": "move",
    "x": 922.5,
    "y": 734.515625,
    "time": 2.1505
  },
  {
    "type": "move",
    "x": 898.61328125,
    "y": 734.515625,
    "time": 2.1586
  },
  {
    "type": "move",
    "x": 857.109375,
    "y": 734.515625,
    "time": 2.1668
  },
  {
    "type": "move",
    "x": 829.28515625,
    "y": 732.375,
    "time": 2.175
  },
  {
    "type": "move",
    "x": 815.38671875,
    "y": 727.7421875,
    "time": 2.1829
  },
  {
    "type": "move",
    "x": 791.5,
    "y": 719.77734375,
    "time": 2.1911
  },
  {
    "type": "move",
    "x": 763.67578125,
    "y": 709.07421875,
    "time": 2.1991
  },
  {
    "type": "move",
    "x": 737.9921875,
    "y": 696.23046875,
    "time": 2.2074
  },
  {
    "type": "move",
    "x": 714.44921875,
    "y": 681.24609375,
    "time": 2.2155
  },
  {
    "type": "move",
    "x": 694.54296875,
    "y": 667.3125,
    "time": 2.2237
  },
  {
    "type": "move",
    "x": 674.63671875,
    "y": 653.37890625,
    "time": 2.2322
  },
  {
    "type": "move",
    "x": 659.90625,
    "y": 638.6484375,
    "time": 2.2401
  },
  {
    "type": "move",
    "x": 648.05859375,
    "y": 625.109375,
    "time": 2.2482
  },
  {
    "type": "move",
    "x": 640.3359375,
    "y": 612.75390625,
    "time": 2.256
  },
  {
    "type": "move",
    "x": 634.15625,
    "y": 598.85546875,
    "time": 2.2643
  },
  {
    "type": "move",
    "x": 629.5234375,
    "y": 584.95703125,
    "time": 2.2724
  },
  {
    "type": "move",
    "x": 627.828125,
    "y": 568.03125,
    "time": 2.2806
  },
  {
    "type": "move",
    "x": 625.3828125,
    "y": 531.3984375,
    "time": 2.2886
  },
  {
    "type": "move",
    "x": 625.3828125,
    "y": 507.51171875,
    "time": 2.2967
  },
  {
    "type": "move",
    "x": 625.3828125,
    "y": 479.6875,
    "time": 2.3047
  },
  {
    "type": "move",
    "x": 633.34375,
    "y": 455.80078125,
    "time": 2.3128
  },
  {
    "type": "move",
    "x": 644.04296875,
    "y": 427.9765625,
    "time": 2.3208
  },
  {
    "type": "move",
    "x": 651.76171875,
    "y": 415.62109375,
    "time": 2.3291
  },
  {
    "type": "move",
    "x": 682.2890625,
    "y": 363.71875,
    "time": 2.3372
  },
  {
    "type": "move",
    "x": 691.55078125,
    "y": 352.90625,
    "time": 2.3451
  },
  {
    "type": "move",
    "x": 712.1640625,
    "y": 327.70703125,
    "time": 2.3533
  },
  {
    "type": "move",
    "x": 730.07421875,
    "y": 309.79296875,
    "time": 2.3614
  },
  {
    "type": "move",
    "x": 747.984375,
    "y": 293.8671875,
    "time": 2.3694
  },
  {
    "type": "move",
    "x": 767.88671875,
    "y": 279.93359375,
    "time": 2.3776
  },
  {
    "type": "move",
    "x": 786.29296875,
    "y": 268.88671875,
    "time": 2.3856
  },
  {
    "type": "move",
    "x": 806.54296875,
    "y": 261.51953125,
    "time": 2.3938
  },
  {
    "type": "move",
    "x": 823.46484375,
    "y": 256.44140625,
    "time": 2.4017
  },
  {
    "type": "move",
    "x": 843.71484375,
    "y": 254.59765625,
    "time": 2.41
  },
  {
    "type": "move",
    "x": 863.96484375,
    "y": 254.59765625,
    "time": 2.418
  },
  {
    "type": "move",
    "x": 884.21484375,
    "y": 254.59765625,
    "time": 2.4261
  },
  {
    "type": "move",
    "x": 904.46484375,
    "y": 254.59765625,
    "time": 2.4341
  },
  {
    "type": "move",
    "x": 921.38671875,
    "y": 261.36328125,
    "time": 2.4424
  },
  {
    "type": "move",
    "x": 939.79296875,
    "y": 272.40625,
    "time": 2.4503
  },
  {
    "type": "move",
    "x": 957.703125,
    "y": 288.328125,
    "time": 2.4585
  },
  {
    "type": "move",
    "x": 972.4296875,
    "y": 303.0546875,
    "time": 2.4667
  },
  {
    "type": "move",
    "x": 988.3515625,
    "y": 320.96484375,
    "time": 2.4748
  },
  {
    "type": "move",
    "x": 998.50390625,
    "y": 336.19140625,
    "time": 2.4829
  },
  {
    "type": "move",
    "x": 1009.546875,
    "y": 354.59765625,
    "time": 2.4911
  },
  {
    "type": "move",
    "x": 1021.48828125,
    "y": 376.48828125,
    "time": 2.4985
  },
  {
    "type": "move",
    "x": 1028.8515625,
    "y": 396.73828125,
    "time": 2.5069
  },
  {
    "type": "move",
    "x": 1036.21484375,
    "y": 416.98828125,
    "time": 2.515
  },
  {
    "type": "move",
    "x": 1040.1953125,
    "y": 440.87109375,
    "time": 2.5229
  },
  {
    "type": "move",
    "x": 1046.1640625,
    "y": 464.75390625,
    "time": 2.531
  },
  {
    "type": "move",
    "x": 1048.15234375,
    "y": 488.63671875,
    "time": 2.5396
  },
  {
    "type": "move",
    "x": 1050.140625,
    "y": 512.51953125,
    "time": 2.5472
  },
  {
    "type": "move",
    "x": 1050.140625,
    "y": 532.76953125,
    "time": 2.5553
  },
  {
    "type": "move",
    "x": 1050.140625,
    "y": 553.01953125,
    "time": 2.5635
  },
  {
    "type": "move",
    "x": 1050.140625,
    "y": 573.26953125,
    "time": 2.5716
  },
  {
    "type": "move",
    "x": 1050.140625,
    "y": 587.1640625,
    "time": 2.5801
  },
  {
    "type": "move",
    "x": 1050.140625,
    "y": 601.05859375,
    "time": 2.588
  },
  {
    "type": "move",
    "x": 1045.94921875,
    "y": 612.23046875,
    "time": 2.5961
  },
  {
    "type": "move",
    "x": 1040.359375,
    "y": 623.40234375,
    "time": 2.6042
  },
  {
    "type": "move",
    "x": 1034.76953125,
    "y": 633.1796875,
    "time": 2.6122
  },
  {
    "type": "move",
    "x": 1028.51953125,
    "y": 640.67578125,
    "time": 2.6202
  },
  {
    "type": "move",
    "x": 1022.26953125,
    "y": 648.171875,
    "time": 2.6284
  },
  {
    "type": "move",
    "x": 1012.48828125,
    "y": 655.15234375,
    "time": 2.6365
  },
  {
    "type": "move",
    "x": 998.94921875,
    "y": 665.3046875,
    "time": 2.6447
  },
  {
    "type": "move",
    "x": 982.0234375,
    "y": 672.0703125,
    "time": 2.6524
  },
  {
    "type": "move",
    "x": 965.09765625,
    "y": 677.14453125,
    "time": 2.6605
  },
  {
    "type": "move",
    "x": 941.2109375,
    "y": 683.11328125,
    "time": 2.6685
  },
  {
    "type": "move",
    "x": 920.95703125,
    "y": 686.79296875,
    "time": 2.6768
  },
  {
    "type": "move",
    "x": 893.1328125,
    "y": 688.9296875,
    "time": 2.6849
  },
  {
    "type": "move",
    "x": 869.24609375,
    "y": 690.91796875,
    "time": 2.6931
  },
  {
    "type": "move",
    "x": 841.421875,
    "y": 690.91796875,
    "time": 2.7009
  },
  {
    "type": "move",
    "x": 817.53515625,
    "y": 690.91796875,
    "time": 2.7092
  },
  {
    "type": "move",
    "x": 793.6484375,
    "y": 686.93359375,
    "time": 2.7173
  },
  {
    "type": "move",
    "x": 776.72265625,
    "y": 681.85546875,
    "time": 2.7254
  },
  {
    "type": "move",
    "x": 754.828125,
    "y": 671.90234375,
    "time": 2.7335
  },
  {
    "type": "move",
    "x": 736.41796875,
    "y": 660.85546875,
    "time": 2.7416
  },
  {
    "type": "move",
    "x": 722.87890625,
    "y": 650.69921875,
    "time": 2.7496
  },
  {
    "type": "move",
    "x": 707.6484375,
    "y": 640.54296875,
    "time": 2.7577
  },
  {
    "type": "move",
    "x": 696.8359375,
    "y": 629.73046875,
    "time": 2.7657
  },
  {
    "type": "move",
    "x": 687.5703125,
    "y": 618.91796875,
    "time": 2.7739
  },
  {
    "type": "move",
    "x": 679.84765625,
    "y": 606.5625,
    "time": 2.7825
  },
  {
    "type": "move",
    "x": 674.2578125,
    "y": 596.78125,
    "time": 2.7903
  },
  {
    "type": "move",
    "x": 670.5078125,
    "y": 588.03125,
    "time": 2.7984
  },
  {
    "type": "move",
    "x": 667.7109375,
    "y": 576.85546875,
    "time": 2.8067
  },
  {
    "type": "move",
    "x": 666.1640625,
    "y": 562.95703125,
    "time": 2.8147
  },
  {
    "type": "move",
    "x": 666.1640625,
    "y": 549.05859375,
    "time": 2.8228
  },
  {
    "type": "move",
    "x": 666.1640625,
    "y": 535.16015625,
    "time": 2.831
  },
  {
    "type": "move",
    "x": 669.546875,
    "y": 518.234375,
    "time": 2.8389
  },
  {
    "type": "move",
    "x": 679.49609375,
    "y": 496.33984375,
    "time": 2.8469
  },
  {
    "type": "move",
    "x": 699.03125,
    "y": 464.59375,
    "time": 2.8549
  },
  {
    "type": "move",
    "x": 708.29296875,
    "y": 453.78125,
    "time": 2.863
  },
  {
    "type": "move",
    "x": 743.08203125,
    "y": 413.1875,
    "time": 2.8711
  },
  {
    "type": "move",
    "x": 753.890625,
    "y": 403.921875,
    "time": 2.8793
  },
  {
    "type": "move",
    "x": 775.2890625,
    "y": 384.66015625,
    "time": 2.8875
  },
  {
    "type": "move",
    "x": 798.828125,
    "y": 367.53515625,
    "time": 2.8957
  },
  {
    "type": "move",
    "x": 824.5078125,
    "y": 352.55078125,
    "time": 2.9039
  },
  {
    "type": "move",
    "x": 846.3984375,
    "y": 340.60546875,
    "time": 2.9119
  },
  {
    "type": "move",
    "x": 870.28125,
    "y": 332.640625,
    "time": 2.9199
  },
  {
    "type": "move",
    "x": 894.1640625,
    "y": 326.66796875,
    "time": 2.9278
  },
  {
    "type": "move",
    "x": 914.4140625,
    "y": 324.82421875,
    "time": 2.9359
  },
  {
    "type": "move",
    "x": 934.6640625,
    "y": 324.82421875,
    "time": 2.9443
  },
  {
    "type": "move",
    "x": 954.9140625,
    "y": 324.82421875,
    "time": 2.9526
  },
  {
    "type": "move",
    "x": 971.8359375,
    "y": 324.82421875,
    "time": 2.961
  },
  {
    "type": "move",
    "x": 990.2421875,
    "y": 334.02734375,
    "time": 2.969
  },
  {
    "type": "move",
    "x": 1003.77734375,
    "y": 344.1796875,
    "time": 2.9769
  },
  {
    "type": "move",
    "x": 1020.34375,
    "y": 357.0625,
    "time": 2.9849
  },
  {
    "type": "move",
    "x": 1031.15234375,
    "y": 367.87109375,
    "time": 2.9931
  },
  {
    "type": "move",
    "x": 1044.03515625,
    "y": 384.4375,
    "time": 3.0012
  },
  {
    "type": "move",
    "x": 1054.1875,
    "y": 399.6640625,
    "time": 3.0092
  },
  {
    "type": "move",
    "x": 1064.33984375,
    "y": 414.890625,
    "time": 3.0175
  },
  {
    "type": "move",
    "x": 1071.10546875,
    "y": 431.8125,
    "time": 3.0254
  },
  {
    "type": "move",
    "x": 1077.87109375,
    "y": 448.734375,
    "time": 3.0331
  },
  {
    "type": "move",
    "x": 1080.95703125,
    "y": 462.62890625,
    "time": 3.0413
  },
  {
    "type": "move",
    "x": 1084.33984375,
    "y": 479.55078125,
    "time": 3.0493
  },
  {
    "type": "move",
    "x": 1086.03125,
    "y": 496.47265625,
    "time": 3.0577
  },
  {
    "type": "move",
    "x": 1087.57421875,
    "y": 510.3671875,
    "time": 3.0658
  },
  {
    "type": "move",
    "x": 1089.1171875,
    "y": 524.26171875,
    "time": 3.0736
  },
  {
    "type": "move",
    "x": 1089.1171875,
    "y": 538.15625,
    "time": 3.082
  },
  {
    "type": "move",
    "x": 1089.1171875,
    "y": 546.90234375,
    "time": 3.0898
  },
  {
    "type": "move",
    "x": 1089.1171875,
    "y": 558.07421875,
    "time": 3.098
  },
  {
    "type": "move",
    "x": 1087.8671875,
    "y": 566.8203125,
    "time": 3.1059
  },
  {
    "type": "move",
    "x": 1084.1171875,
    "y": 575.56640625,
    "time": 3.1141
  },
  {
    "type": "move",
    "x": 1080.8046875,
    "y": 582.1875,
    "time": 3.1222
  },
  {
    "type": "move",
    "x": 1075.8046875,
    "y": 589.68359375,
    "time": 3.1303
  },
  {
    "type": "move",
    "x": 1070.8046875,
    "y": 597.1796875,
    "time": 3.1384
  },
  {
    "type": "move",
    "x": 1064.5546875,
    "y": 603.42578125,
    "time": 3.1465
  },
  {
    "type": "move",
    "x": 1057.0546875,
    "y": 609.671875,
    "time": 3.1545
  },
  {
    "type": "move",
    "x": 1049.5546875,
    "y": 614.66796875,
    "time": 3.1627
  },
  {
    "type": "move",
    "x": 1038.37890625,
    "y": 618.85546875,
    "time": 3.1708
  },
  {
    "type": "move",
    "x": 1024.48046875,
    "y": 623.484375,
    "time": 3.1789
  },
  {
    "type": "move",
    "x": 1010.58203125,
    "y": 625.02734375,
    "time": 3.1869
  },
  {
    "type": "move",
    "x": 993.65625,
    "y": 626.71875,
    "time": 3.1952
  },
  {
    "type": "move",
    "x": 979.7578125,
    "y": 626.71875,
    "time": 3.2031
  },
  {
    "type": "move",
    "x": 962.83203125,
    "y": 626.71875,
    "time": 3.2113
  },
  {
    "type": "move",
    "x": 945.90625,
    "y": 626.71875,
    "time": 3.2193
  },
  {
    "type": "move",
    "x": 928.98046875,
    "y": 626.71875,
    "time": 3.2274
  },
  {
    "type": "move",
    "x": 912.0546875,
    "y": 621.640625,
    "time": 3.2353
  },
  {
    "type": "move",
    "x": 898.15625,
    "y": 617.0078125,
    "time": 3.2434
  },
  {
    "type": "move",
    "x": 884.2578125,
    "y": 610.828125,
    "time": 3.2516
  },
  {
    "type": "move",
    "x": 869.02734375,
    "y": 602.36328125,
    "time": 3.2599
  },
  {
    "type": "move",
    "x": 853.796875,
    "y": 593.8984375,
    "time": 3.268
  },
  {
    "type": "move",
    "x": 841.44140625,
    "y": 586.17578125,
    "time": 3.2759
  },
  {
    "type": "move",
    "x": 830.62890625,
    "y": 576.91015625,
    "time": 3.2846
  },
  {
    "type": "move",
    "x": 823.12890625,
    "y": 570.66015625,
    "time": 3.2924
  },
  {
    "type": "move",
    "x": 814.74609375,
    "y": 562.27734375,
    "time": 3.3004
  },
  {
    "type": "move",
    "x": 813.1171875,
    "y": 559.0234375,
    "time": 3.3087
  },
  {
    "type": "move",
    "x": 806.8671875,
    "y": 551.5234375,
    "time": 3.3166
  },
  {
    "type": "move",
    "x": 803.5546875,
    "y": 544.8984375,
    "time": 3.3248
  },
  {
    "type": "move",
    "x": 800.2421875,
    "y": 538.2734375,
    "time": 3.333
  },
  {
    "type": "move",
    "x": 799.13671875,
    "y": 531.6484375,
    "time": 3.3411
  },
  {
    "type": "move",
    "x": 796.33984375,
    "y": 520.47265625,
    "time": 3.3492
  },
  {
    "type": "move",
    "x": 796.33984375,
    "y": 511.72265625,
    "time": 3.3575
  },
  {
    "type": "move",
    "x": 796.33984375,
    "y": 502.97265625,
    "time": 3.3654
  },
  {
    "type": "move",
    "x": 796.33984375,
    "y": 491.796875,
    "time": 3.3736
  },
  {
    "type": "move",
    "x": 799.1328125,
    "y": 480.62109375,
    "time": 3.3816
  },
  {
    "type": "move",
    "x": 806.8515625,
    "y": 468.265625,
    "time": 3.3896
  },
  {
    "type": "move",
    "x": 818.6953125,
    "y": 454.7265625,
    "time": 3.3977
  },
  {
    "type": "move",
    "x": 830.5390625,
    "y": 441.1875,
    "time": 3.4057
  },
  {
    "type": "move",
    "x": 845.265625,
    "y": 426.45703125,
    "time": 3.4139
  },
  {
    "type": "move",
    "x": 858.80078125,
    "y": 414.609375,
    "time": 3.4217
  },
  {
    "type": "move",
    "x": 872.3359375,
    "y": 404.453125,
    "time": 3.4295
  },
  {
    "type": "move",
    "x": 886.23046875,
    "y": 398.2734375,
    "time": 3.4378
  },
  {
    "type": "move",
    "x": 897.40234375,
    "y": 392.68359375,
    "time": 3.4458
  },
  {
    "type": "move",
    "x": 908.57421875,
    "y": 389.88671875,
    "time": 3.4539
  },
  {
    "type": "move",
    "x": 913.36328125,
    "y": 388.92578125,
    "time": 3.4621
  },
  {
    "type": "move",
    "x": 930.28515625,
    "y": 387.23046875,
    "time": 3.4702
  },
  {
    "type": "move",
    "x": 941.45703125,
    "y": 387.23046875,
    "time": 3.4785
  },
  {
    "type": "move",
    "x": 950.203125,
    "y": 387.23046875,
    "time": 3.4865
  },
  {
    "type": "move",
    "x": 956.82421875,
    "y": 387.23046875,
    "time": 3.4947
  },
  {
    "type": "move",
    "x": 965.5703125,
    "y": 387.23046875,
    "time": 3.5027
  },
  {
    "type": "move",
    "x": 972.19140625,
    "y": 389.4375,
    "time": 3.5109
  },
  {
    "type": "move",
    "x": 979.6875,
    "y": 394.43359375,
    "time": 3.5188
  },
  {
    "type": "move",
    "x": 985.93359375,
    "y": 400.6796875,
    "time": 3.5271
  },
  {
    "type": "move",
    "x": 990.34765625,
    "y": 406.1953125,
    "time": 3.5352
  },
  {
    "type": "move",
    "x": 995.34375,
    "y": 413.69140625,
    "time": 3.5432
  },
  {
    "type": "move",
    "x": 998.65234375,
    "y": 420.3125,
    "time": 3.5512
  },
  {
    "type": "move",
    "x": 1002.3984375,
    "y": 429.05859375,
    "time": 3.559
  },
  {
    "type": "move",
    "x": 1005.19140625,
    "y": 440.23046875,
    "time": 3.567
  },
  {
    "type": "move",
    "x": 1006.5859375,
    "y": 451.40234375,
    "time": 3.5757
  },
  {
    "type": "move",
    "x": 1007.98046875,
    "y": 462.57421875,
    "time": 3.5836
  },
  {
    "type": "move",
    "x": 1009.5234375,
    "y": 476.46875,
    "time": 3.5915
  },
  {
    "type": "move",
    "x": 1011.06640625,
    "y": 490.36328125,
    "time": 3.5995
  },
  {
    "type": "move",
    "x": 1011.06640625,
    "y": 501.53515625,
    "time": 3.6077
  },
  {
    "type": "move",
    "x": 1011.06640625,
    "y": 512.70703125,
    "time": 3.616
  },
  {
    "type": "move",
    "x": 1011.06640625,
    "y": 523.87890625,
    "time": 3.624
  },
  {
    "type": "move",
    "x": 1011.06640625,
    "y": 535.05078125,
    "time": 3.6322
  },
  {
    "type": "move",
    "x": 1009.4375,
    "y": 538.30078125,
    "time": 3.64
  },
  {
    "type": "move",
    "x": 1006.9375,
    "y": 547.046875,
    "time": 3.6482
  },
  {
    "type": "move",
    "x": 1004.7265625,
    "y": 553.66796875,
    "time": 3.6562
  },
  {
    "type": "move",
    "x": 999.7265625,
    "y": 561.1640625,
    "time": 3.6643
  },
  {
    "type": "move",
    "x": 996.8515625,
    "y": 565.953125,
    "time": 3.6726
  },
  {
    "type": "move",
    "x": 992.43359375,
    "y": 571.46875,
    "time": 3.6809
  },
  {
    "type": "move",
    "x": 988.015625,
    "y": 576.984375,
    "time": 3.6891
  },
  {
    "type": "move",
    "x": 984.1796875,
    "y": 579.85546875,
    "time": 3.6972
  },
  {
    "type": "move",
    "x": 980.34375,
    "y": 583.6875,
    "time": 3.7051
  },
  {
    "type": "move",
    "x": 975.55078125,
    "y": 585.6015625,
    "time": 3.7131
  },
  {
    "type": "move",
    "x": 966.80078125,
    "y": 589.34765625,
    "time": 3.7212
  },
  {
    "type": "move",
    "x": 960.17578125,
    "y": 590.44921875,
    "time": 3.7293
  },
  {
    "type": "move",
    "x": 951.42578125,
    "y": 590.44921875,
    "time": 3.7374
  },
  {
    "type": "move",
    "x": 942.67578125,
    "y": 590.44921875,
    "time": 3.7453
  },
  {
    "type": "move",
    "x": 931.5,
    "y": 590.44921875,
    "time": 3.7533
  },
  {
    "type": "move",
    "x": 922.75,
    "y": 589.19921875,
    "time": 3.7614
  },
  {
    "type": "move",
    "x": 912.96875,
    "y": 583.609375,
    "time": 3.7695
  },
  {
    "type": "move",
    "x": 904.21875,
    "y": 579.859375,
    "time": 3.7776
  },
  {
    "type": "move",
    "x": 900.3828125,
    "y": 576.0234375,
    "time": 3.7859
  },
  {
    "type": "move",
    "x": 892.8828125,
    "y": 571.0234375,
    "time": 3.7944
  },
  {
    "type": "move",
    "x": 886.6328125,
    "y": 564.7734375,
    "time": 3.8023
  },
  {
    "type": "move",
    "x": 882.796875,
    "y": 560.9375,
    "time": 3.8104
  },
  {
    "type": "move",
    "x": 880.35546875,
    "y": 558.49609375,
    "time": 3.8184
  },
  {
    "type": "move",
    "x": 879.68359375,
    "y": 556.48828125,
    "time": 3.8266
  },
  {
    "type": "move",
    "x": 879.01171875,
    "y": 554.48046875,
    "time": 3.8345
  },
  {
    "type": "move",
    "x": 879.01171875,
    "y": 554.09765625,
    "time": 3.8427
  },
  {
    "type": "move",
    "x": 879.01171875,
    "y": 553.71484375,
    "time": 3.8507
  },
  {
    "type": "key",
    "key": "Key.ctrl",
    "time": 6.0709
  },
  {
    "type": "key",
    "key": "s",
    "time": 6.6347
  },
  {
    "type": "key",
    "key": "t",
    "time": 6.8521
  },
  {
    "type": "key",
    "key": "o",
    "time": 7.2842
  }
]